<?xml version='1.0' encoding='UTF-8'?>
<document filename="1503.03074_19"><tableRegion><Coords points="81,353 511,353 81,422 511,422" /></tableRegion><tableRegion><Coords points="121,226 471,226 121,307 471,307" /></tableRegion><tableRegion><Coords points="42,562 595,562 42,613 595,613" /></tableRegion><tableRegion><Coords points="42,659 595,659 42,710 595,710" /></tableRegion><tableRegion><Coords points="110,457 481,457 110,527 481,527" /></tableRegion><tableRegion><Coords points="149,118 446,118 149,180 446,180" /></tableRegion></document>