<?xml version='1.0' encoding='UTF-8'?>
<document filename="1802.04712_11"><tableRegion><Coords points="56,382 537,382 56,458 537,458" /></tableRegion><tableRegion><Coords points="78,234 273,234 78,345 273,345" /></tableRegion><tableRegion><Coords points="76,620 274,620 76,720 274,720" /></tableRegion><tableRegion><Coords points="179,90 415,90 179,165 415,165" /></tableRegion><tableRegion><Coords points="355,620 499,620 355,720 499,720" /></tableRegion><tableRegion><Coords points="364,234 490,234 364,345 490,345" /></tableRegion></document>