<?xml version='1.0' encoding='UTF-8'?>
<document filename="1809.00799_18"><tableRegion><Coords points="152,292 295,292 152,356 295,356" /></tableRegion><tableRegion><Coords points="306,294 440,294 306,354 440,354" /></tableRegion><tableRegion><Coords points="229,369 363,369 229,418 363,418" /></tableRegion><tableRegion><Coords points="150,505 291,505 150,551 291,551" /></tableRegion><tableRegion><Coords points="301,505 441,505 301,551 441,551" /></tableRegion><tableRegion><Coords points="150,564 291,564 150,607 291,607" /></tableRegion><tableRegion><Coords points="301,564 441,564 301,607 441,607" /></tableRegion></document>